sphero_bolt_plus/__init__.py
sphero_bolt_plus/exceptions.py
sphero_bolt_plus/robot.py
sphero_bolt_plus/scanner.py
sphero_bolt_plus/types.py
sphero_bolt_plus-1.0.1.dist-info/METADATA
sphero_bolt_plus-1.0.1.dist-info/WHEEL
sphero_bolt_plus-1.0.1.dist-info/licenses/LICENSE
sphero_bolt_plus-1.0.1.dist-info/RECORD
