Metadata-Version: 2.4
Name: sphero-bolt-plus
Version: 1.0.1
Summary: Modern Python library for controlling Sphero BOLT+ robots with enhanced features
Project-URL: Homepage, https://github.com/assistant/sphero-bolt-plus
Project-URL: Documentation, https://sphero-bolt-plus.readthedocs.io
Project-URL: Repository, https://github.com/assistant/sphero-bolt-plus
Project-URL: Issues, https://github.com/assistant/sphero-bolt-plus/issues
Author-email: Assistant <assistant@example.com>
License-Expression: MIT
License-File: LICENSE
Keywords: bluetooth,bolt,education,robotics,sphero
Classifier: Development Status :: 4 - Beta
Classifier: Intended Audience :: Developers
Classifier: Intended Audience :: Education
Classifier: License :: OSI Approved :: MIT License
Classifier: Operating System :: OS Independent
Classifier: Programming Language :: Python :: 3
Classifier: Programming Language :: Python :: 3.9
Classifier: Programming Language :: Python :: 3.10
Classifier: Programming Language :: Python :: 3.11
Classifier: Programming Language :: Python :: 3.12
Classifier: Programming Language :: Python :: 3.13
Classifier: Topic :: Education
Classifier: Topic :: Scientific/Engineering
Classifier: Topic :: Software Development :: Libraries :: Python Modules
Requires-Python: >=3.9
Requires-Dist: bleak>=0.20.0
Requires-Dist: typing-extensions>=4.0.0; python_version < '3.11'
Provides-Extra: dev
Requires-Dist: black>=22.0.0; extra == 'dev'
Requires-Dist: mypy>=1.0.0; extra == 'dev'
Requires-Dist: pytest-asyncio>=0.20.0; extra == 'dev'
Requires-Dist: pytest>=7.0.0; extra == 'dev'
Requires-Dist: ruff>=0.0.200; extra == 'dev'
Provides-Extra: docs
Requires-Dist: sphinx-rtd-theme>=1.0.0; extra == 'docs'
Requires-Dist: sphinx>=5.0.0; extra == 'docs'
